PyYTMusic/PyYTMusic.py
PyYTMusic/__init__.py
PyYTMusic/constants.py
PyYTMusic/lyrics.py
PyYTMusic/search.py
PyYTMusic-0.1.5.post1.dist-info/LICENSE
PyYTMusic-0.1.5.post1.dist-info/METADATA
PyYTMusic-0.1.5.post1.dist-info/WHEEL
PyYTMusic-0.1.5.post1.dist-info/top_level.txt
PyYTMusic-0.1.5.post1.dist-info/RECORD
