Metadata-Version: 2.1
Name: PyYTMusic
Version: 0.1.5.post1
Summary: Python Youtube Music API
Home-page: https://github.com/abdulsamedkeskin/PyYTMusic
Author: Samet Keskin
Author-email: Samet Keskin <sametkeskin.py@gmail.com>
License: MIT License        
Project-URL: Homepage, https://github.com/abdulsamedkeskin/PyYTMusic
Project-URL: Bug Tracker, https://github.com/abdulsamedkeskin/PyYTMusic/issues
Keywords: PyYTMusic,Youtube,Music,API
Classifier: Programming Language :: Python :: 3
Classifier: License :: OSI Approved :: MIT License
Classifier: Operating System :: OS Independent
Requires-Python: >=3.7
License-File: LICENSE
